setup.py
laplace/__init__.py
laplace.egg-info/PKG-INFO
laplace.egg-info/SOURCES.txt
laplace.egg-info/dependency_links.txt
laplace.egg-info/not-zip-safe
laplace.egg-info/top_level.txt
z3/__init__.py
z3/z3.py
z3/z3consts.py
z3/z3core.py
z3/z3num.py
z3/z3poly.py
z3/z3printer.py
z3/z3rcf.py
z3/z3types.py
z3/z3util.py